pytest_deadfixtures.py
pytest_deadfixtures-3.0.0.dist-info/licenses/AUTHORS.rst
pytest_deadfixtures-3.0.0.dist-info/licenses/LICENSE
pytest_deadfixtures-3.0.0.dist-info/METADATA
pytest_deadfixtures-3.0.0.dist-info/WHEEL
pytest_deadfixtures-3.0.0.dist-info/entry_points.txt
pytest_deadfixtures-3.0.0.dist-info/top_level.txt
pytest_deadfixtures-3.0.0.dist-info/RECORD
