Metadata-Version: 2.4
Name: pytest-deadfixtures
Version: 3.0.0
Summary: A simple plugin to list unused fixtures in pytest
Home-page: https://github.com/jllorencetti/pytest-deadfixtures
Author: João Luiz Lorencetti
Author-email: me@dirtycoder.net
Maintainer: João Luiz Lorencetti
Maintainer-email: me@dirtycoder.net
License: MIT
Classifier: Development Status :: 5 - Production/Stable
Classifier: Framework :: Pytest
Classifier: Intended Audience :: Developers
Classifier: Topic :: Software Development :: Testing
Classifier: Programming Language :: Python
Classifier: Programming Language :: Python :: 3
Classifier: Programming Language :: Python :: 3.10
Classifier: Programming Language :: Python :: 3.11
Classifier: Programming Language :: Python :: 3.12
Classifier: Programming Language :: Python :: 3.13
Classifier: Programming Language :: Python :: 3.14
Classifier: Programming Language :: Python :: Implementation :: CPython
Classifier: Programming Language :: Python :: Implementation :: PyPy
Classifier: Operating System :: OS Independent
Classifier: License :: OSI Approved :: MIT License
License-File: LICENSE
License-File: AUTHORS.rst
Requires-Dist: pytest>=7.0.0
Dynamic: author
Dynamic: author-email
Dynamic: classifier
Dynamic: description
Dynamic: home-page
Dynamic: license
Dynamic: license-file
Dynamic: maintainer
Dynamic: maintainer-email
Dynamic: requires-dist
Dynamic: summary
